lantern/__init__.py
lantern/early_stopping.py
lantern/epochs.py
lantern/functional_base.py
lantern/git_info.py
lantern/lambda_module.py
lantern/metric.py
lantern/metric_table.py
lantern/module_device.py
lantern/module_train.py
lantern/numpy.py
lantern/numpy_seed.py
lantern/progress_bar.py
lantern/requires_grad.py
lantern/set_learning_rate.py
lantern/set_seeds.py
lantern/star.py
lantern/tensor.py
lantern/worker_init_fn.py
pytorch_lantern-0.12.14.dist-info/LICENSE
pytorch_lantern-0.12.14.dist-info/WHEEL
pytorch_lantern-0.12.14.dist-info/METADATA
pytorch_lantern-0.12.14.dist-info/RECORD
