Metadata-Version: 2.1
Name: pytorch-lantern
Version: 0.12.14
Summary: Pytorch project template and related tools
Home-page: https://github.com/nextml-code/pytorch-lantern
License: Apache-2.0
Keywords: pytorch,machine,learning
Author: NextML AB
Requires-Python: >=3.8,<4.0
Classifier: Development Status :: 3 - Alpha
Classifier: Environment :: Other Environment
Classifier: Intended Audience :: Developers
Classifier: Intended Audience :: Science/Research
Classifier: License :: OSI Approved :: Apache Software License
Classifier: Operating System :: OS Independent
Classifier: Programming Language :: Python :: 3
Classifier: Programming Language :: Python :: 3.8
Classifier: Programming Language :: Python :: 3.9
Classifier: Programming Language :: Python :: 3.10
Classifier: Programming Language :: Python :: 3.11
Classifier: Topic :: Scientific/Engineering
Classifier: Topic :: Scientific/Engineering :: Artificial Intelligence
Classifier: Topic :: Software Development
Classifier: Topic :: Software Development :: Libraries
Classifier: Topic :: Software Development :: Libraries :: Python Modules
Provides-Extra: training
Requires-Dist: numpy (>=1.19.4,<2.0.0)
Requires-Dist: pandas (>=1.0.0,<2.0.0)
Requires-Dist: pydantic (>=2.0.0,<3.0.0)
Requires-Dist: pydantic-core (>=2.14.5,<3.0.0)
Requires-Dist: tensorboard (>=2.2.0,<3.0.0); extra == "training"
Requires-Dist: torch (>=1.6.0)
Requires-Dist: tqdm
Project-URL: Documentation, https://pytorch-lantern.readthedocs.io
Project-URL: Repository, https://github.com/nextml-code/pytorch-lantern
